hoshrust-0.211225.0.dist-info/METADATA
hoshrust-0.211225.0.dist-info/WHEEL
hoshrust/hash.py
hoshrust/__pycache__/colors.cpython-38.pyc
hoshrust/__pycache__/hash.cpython-38.pyc
hoshrust/__pycache__/colors.cpython-37.pyc
hoshrust/__pycache__/hash.cpython-37.pyc
hoshrust/__pycache__/__init__.cpython-37.pyc
hoshrust/__pycache__/__init__.cpython-38.pyc
hoshrust/colors.py
hoshrust/__init__.py
hoshrust/hoshrust.cpython-39-x86_64-linux-gnu.so
hoshrust-0.211225.0.dist-info/RECORD
