Metadata-Version: 2.1
Name: hoshrust
Version: 0.211225.0
Requires-Dist: colored==1.4.2
Requires-Dist: toml==0.10.0
Author: davips <dpsabc@gmail.com>
Author-Email: davips <dpsabc@gmail.com>
Maintainer: davips
Maintainer-Email: dpsabc@gmail.com
